{
"meta":{"test_sets":[],"test_metrics":[],"learn_metrics":[{"best_value":"Min","name":"RMSE"}],"launch_mode":"Train","parameters":"","iteration_count":100,"learn_sets":["learn"],"name":"experiment"},
"iterations":[
{"learn":[14.005006],"iteration":0,"passed_time":0.001638221019,"remaining_time":0.1621838809},
{"learn":[13.14441192],"iteration":1,"passed_time":0.003166556458,"remaining_time":0.1551612664},
{"learn":[12.34258257],"iteration":2,"passed_time":0.004598962347,"remaining_time":0.1486997825},
{"learn":[11.64527793],"iteration":3,"passed_time":0.005830754908,"remaining_time":0.1399381178},
{"learn":[11.02766183],"iteration":4,"passed_time":0.007988346076,"remaining_time":0.1517785754},
{"learn":[10.43485794],"iteration":5,"passed_time":0.009865711666,"remaining_time":0.1545628161},
{"learn":[9.890641275],"iteration":6,"passed_time":0.01127061558,"remaining_time":0.1497381784},
{"learn":[9.492161212],"iteration":7,"passed_time":0.01293573297,"remaining_time":0.1487609291},
{"learn":[9.105082953],"iteration":8,"passed_time":0.01450259764,"remaining_time":0.1466373762},
{"learn":[8.674157135],"iteration":9,"passed_time":0.01610815198,"remaining_time":0.1449733678},
{"learn":[8.341743544],"iteration":10,"passed_time":0.01780014168,"remaining_time":0.1440193281},
{"learn":[8.049372916],"iteration":11,"passed_time":0.0194316198,"remaining_time":0.1424985452},
{"learn":[7.757318612],"iteration":12,"passed_time":0.02114105679,"remaining_time":0.141482457},
{"learn":[7.522206899],"iteration":13,"passed_time":0.02300711839,"remaining_time":0.1413294415},
{"learn":[7.297756655],"iteration":14,"passed_time":0.02470648566,"remaining_time":0.1400034187},
{"learn":[7.088359431],"iteration":15,"passed_time":0.02640511297,"remaining_time":0.1386268431},
{"learn":[6.882113791],"iteration":16,"passed_time":0.0278878855,"remaining_time":0.1361584998},
{"learn":[6.704728832],"iteration":17,"passed_time":0.02931561198,"remaining_time":0.133548899},
{"learn":[6.563881962],"iteration":18,"passed_time":0.03076696915,"remaining_time":0.1311644474},
{"learn":[6.418790279],"iteration":19,"passed_time":0.03233461891,"remaining_time":0.1293384756},
{"learn":[6.315756953],"iteration":20,"passed_time":0.03385192408,"remaining_time":0.1273477144},
{"learn":[6.210157751],"iteration":21,"passed_time":0.03549278511,"remaining_time":0.1258380563},
{"learn":[6.115058449],"iteration":22,"passed_time":0.03732227466,"remaining_time":0.1249484847},
{"learn":[6.014819884],"iteration":23,"passed_time":0.03871639094,"remaining_time":0.1226019047},
{"learn":[5.93117229],"iteration":24,"passed_time":0.04019013853,"remaining_time":0.1205704156},
{"learn":[5.844857622],"iteration":25,"passed_time":0.04171682058,"remaining_time":0.1187324894},
{"learn":[5.771145213],"iteration":26,"passed_time":0.0436151117,"remaining_time":0.117922339},
{"learn":[5.704018229],"iteration":27,"passed_time":0.04529551064,"remaining_time":0.1164741702},
{"learn":[5.665806474],"iteration":28,"passed_time":0.04685562741,"remaining_time":0.1147155016},
{"learn":[5.616500369],"iteration":29,"passed_time":0.04823183919,"remaining_time":0.1125409581},
{"learn":[5.558023666],"iteration":30,"passed_time":0.04962841199,"remaining_time":0.1104632396},
{"learn":[5.510080976],"iteration":31,"passed_time":0.05138754786,"remaining_time":0.1091985392},
{"learn":[5.468747792],"iteration":32,"passed_time":0.05312144977,"remaining_time":0.1078526404},
{"learn":[5.429275534],"iteration":33,"passed_time":0.05453293214,"remaining_time":0.1058580447},
{"learn":[5.402117324],"iteration":34,"passed_time":0.05626742461,"remaining_time":0.1044966457},
{"learn":[5.367635151],"iteration":35,"passed_time":0.05790486055,"remaining_time":0.1029419743},
{"learn":[5.345181232],"iteration":36,"passed_time":0.05925361046,"remaining_time":0.1008912827},
{"learn":[5.319151269],"iteration":37,"passed_time":0.0608017715,"remaining_time":0.09920289034},
{"learn":[5.296134146],"iteration":38,"passed_time":0.06213745674,"remaining_time":0.09718935542},
{"learn":[5.269629003],"iteration":39,"passed_time":0.06350922874,"remaining_time":0.09526384311},
{"learn":[5.251147059],"iteration":40,"passed_time":0.06504879598,"remaining_time":0.09360680397},
{"learn":[5.248003302],"iteration":41,"passed_time":0.06571971226,"remaining_time":0.09075579312},
{"learn":[5.232376509],"iteration":42,"passed_time":0.06768918626,"remaining_time":0.08972752597},
{"learn":[5.213524255],"iteration":43,"passed_time":0.06921192685,"remaining_time":0.0880879069},
{"learn":[5.189691584],"iteration":44,"passed_time":0.07090449508,"remaining_time":0.08666104954},
{"learn":[5.166052198],"iteration":45,"passed_time":0.07234782997,"remaining_time":0.08493006127},
{"learn":[5.140406659],"iteration":46,"passed_time":0.07370619539,"remaining_time":0.08311549693},
{"learn":[5.118929684],"iteration":47,"passed_time":0.07509621681,"remaining_time":0.08135423488},
{"learn":[5.108792602],"iteration":48,"passed_time":0.07655813401,"remaining_time":0.0796829558},
{"learn":[5.098141225],"iteration":49,"passed_time":0.07808301027,"remaining_time":0.07808301027},
{"learn":[5.085926393],"iteration":50,"passed_time":0.07953057939,"remaining_time":0.07641173314},
{"learn":[5.067816804],"iteration":51,"passed_time":0.08094981734,"remaining_time":0.07472290831},
{"learn":[5.049834901],"iteration":52,"passed_time":0.08268485526,"remaining_time":0.07332430561},
{"learn":[5.03838627],"iteration":53,"passed_time":0.08424519462,"remaining_time":0.07176442505},
{"learn":[5.033534248],"iteration":54,"passed_time":0.08534718977,"remaining_time":0.0698295189},
{"learn":[5.023726885],"iteration":55,"passed_time":0.0875733549,"remaining_time":0.06880763599},
{"learn":[5.01290392],"iteration":56,"passed_time":0.08932428298,"remaining_time":0.06738498541},
{"learn":[5.005569127],"iteration":57,"passed_time":0.09066586888,"remaining_time":0.06565459471},
{"learn":[4.989969032],"iteration":58,"passed_time":0.09237013315,"remaining_time":0.06418941456},
{"learn":[4.976762446],"iteration":59,"passed_time":0.0940283793,"remaining_time":0.0626855862},
{"learn":[4.967222715],"iteration":60,"passed_time":0.0956649339,"remaining_time":0.06116282659},
{"learn":[4.954407599],"iteration":61,"passed_time":0.09736289043,"remaining_time":0.05967402962},
{"learn":[4.942125056],"iteration":62,"passed_time":0.09879539257,"remaining_time":0.05802269088},
{"learn":[4.930230716],"iteration":63,"passed_time":0.1002749065,"remaining_time":0.05640463489},
{"learn":[4.921695642],"iteration":64,"passed_time":0.1020799542,"remaining_time":0.05496612916},
{"learn":[4.906405625],"iteration":65,"passed_time":0.1035122006,"remaining_time":0.05332446699},
{"learn":[4.894330248],"iteration":66,"passed_time":0.1052520944,"remaining_time":0.05184058383},
{"learn":[4.88211557],"iteration":67,"passed_time":0.1066196893,"remaining_time":0.05017397146},
{"learn":[4.877946398],"iteration":68,"passed_time":0.1085741766,"remaining_time":0.04877970252},
{"learn":[4.863182126],"iteration":69,"passed_time":0.109996975,"remaining_time":0.0471415607},
{"learn":[4.84646533],"iteration":70,"passed_time":0.111429068,"remaining_time":0.04551328131},
{"learn":[4.838014752],"iteration":71,"passed_time":0.1130085813,"remaining_time":0.04394778161},
{"learn":[4.82981137],"iteration":72,"passed_time":0.1148018417,"remaining_time":0.04246095514},
{"learn":[4.817094767],"iteration":73,"passed_time":0.1162473082,"remaining_time":0.04084364884},
{"learn":[4.808314151],"iteration":74,"passed_time":0.1176656929,"remaining_time":0.03922189764},
{"learn":[4.796235023],"iteration":75,"passed_time":0.1190756793,"remaining_time":0.0376028461},
{"learn":[4.784434534],"iteration":76,"passed_time":0.1207146052,"remaining_time":0.03605760935},
{"learn":[4.774402487],"iteration":77,"passed_time":0.1222639103,"remaining_time":0.03448469264},
{"learn":[4.76731896],"iteration":78,"passed_time":0.1239554558,"remaining_time":0.03295018445},
{"learn":[4.75934113],"iteration":79,"passed_time":0.1254811583,"remaining_time":0.03137028956},
{"learn":[4.754106378],"iteration":80,"passed_time":0.127199927,"remaining_time":0.02983701992},
{"learn":[4.744002932],"iteration":81,"passed_time":0.1286825351,"remaining_time":0.02824738576},
{"learn":[4.731700554],"iteration":82,"passed_time":0.1301607275,"remaining_time":0.02665942611},
{"learn":[4.723284153],"iteration":83,"passed_time":0.1315900803,"remaining_time":0.0250647772},
{"learn":[4.712232782],"iteration":84,"passed_time":0.1329219885,"remaining_time":0.0234568215},
{"learn":[4.703046867],"iteration":85,"passed_time":0.1344954737,"remaining_time":0.021894612},
{"learn":[4.698601855],"iteration":86,"passed_time":0.1361820872,"remaining_time":0.02034904751},
{"learn":[4.692429407],"iteration":87,"passed_time":0.137919343,"remaining_time":0.01880718313},
{"learn":[4.675027364],"iteration":88,"passed_time":0.1397773763,"remaining_time":0.01727585549},
{"learn":[4.662368584],"iteration":89,"passed_time":0.1421357552,"remaining_time":0.01579286169},
{"learn":[4.646206172],"iteration":90,"passed_time":0.1437487734,"remaining_time":0.01421691165},
{"learn":[4.641245848],"iteration":91,"passed_time":0.1451557568,"remaining_time":0.01262223972},
{"learn":[4.633900435],"iteration":92,"passed_time":0.1467098867,"remaining_time":0.01104267964},
{"learn":[4.624738236],"iteration":93,"passed_time":0.1486508871,"remaining_time":0.009488354498},
{"learn":[4.612798287],"iteration":94,"passed_time":0.1507139515,"remaining_time":0.007932313235},
{"learn":[4.605222001],"iteration":95,"passed_time":0.152358,"remaining_time":0.006348249998},
{"learn":[4.601725912],"iteration":96,"passed_time":0.1538702828,"remaining_time":0.004758874726},
{"learn":[4.59722371],"iteration":97,"passed_time":0.1555811075,"remaining_time":0.003175124642},
{"learn":[4.580235665],"iteration":98,"passed_time":0.1576265581,"remaining_time":0.001592187455},
{"learn":[4.57591791],"iteration":99,"passed_time":0.1589594288,"remaining_time":0}
]}